fdmutils
