Metadata-Version: 1.2
Name: fdmutils
Version: 0.1.2
Summary: independent functions
Home-page: https://github.com/fdmseven/fdmutils
Author: fdmseven
Author-email: wrp2003000@163.com
License: LICENSE.txt
Platform: UNKNOWN
Requires-Python: >=3
